queuelab/__init__.py
queuelab/compare.py
queuelab/formulas.py
queuelab/mm1.py
queuelab/utils.py
queuesim-0.2.0.dist-info/licenses/LICENSE
queuesim-0.2.0.dist-info/METADATA
queuesim-0.2.0.dist-info/WHEEL
queuesim-0.2.0.dist-info/top_level.txt
queuesim-0.2.0.dist-info/RECORD
